{
  "schema_version": "mesh-luma-gated-write-coverage-v1",
  "generated_at": "2026-05-11T01:47:13.596Z",
  "run_id": "mesh-luma-gated-write-coverage-20260511T014707Z-dfc54677",
  "repo": {
    "branch": "coord/mesh-public-wss-release-ready-evidence",
    "commit": "6db6319f54cfe64885eff176945065aaea9d57ea",
    "base_ref": "origin/main",
    "dirty": false
  },
  "run": {
    "mode": "luma_gated_write_coverage",
    "started_at": "2026-05-11T01:47:07.081Z",
    "completed_at": "2026-05-11T01:47:13.596Z",
    "duration_ms": 6515,
    "command": "pnpm test:mesh:luma-gated-write-coverage -- --mode local-e2e"
  },
  "status": "pass",
  "schema_epoch": "post_luma_m0b",
  "luma_profile": "e2e",
  "coverage_source_report_path": null,
  "luma_gated_write_coverage": {
    "status": "pass",
    "command": "pnpm test:mesh:luma-gated-write-coverage -- --mode local-e2e",
    "expected_schema_epoch": "post_luma_m0b",
    "expected_luma_profile": "e2e",
    "source_report_path": null,
    "failures": [],
    "required_write_classes": [
      {
        "write_class": "forum_thread",
        "label": "forum thread",
        "status": "pass",
        "trace_id": "mesh-luma-gated-write-coverage-20260511T014707Z-dfc54677:forum-thread",
        "writer_kind": "luma",
        "reader_path": "luma_reader_path",
        "schema_epoch": "post_luma_m0b",
        "luma_profile": "e2e"
      },
      {
        "write_class": "forum_comment",
        "label": "forum comment",
        "status": "pass",
        "trace_id": "mesh-luma-gated-write-coverage-20260511T014707Z-dfc54677:forum-comment",
        "writer_kind": "luma",
        "reader_path": "luma_reader_path",
        "schema_epoch": "post_luma_m0b",
        "luma_profile": "e2e"
      },
      {
        "write_class": "vote_or_aggregate",
        "label": "vote or aggregate",
        "status": "pass",
        "trace_id": "mesh-luma-gated-write-coverage-20260511T014707Z-dfc54677:vote-or-aggregate",
        "writer_kind": "luma",
        "reader_path": "luma_reader_path",
        "schema_epoch": "post_luma_m0b",
        "luma_profile": "e2e"
      },
      {
        "write_class": "directory_publish",
        "label": "directory publish",
        "status": "pass",
        "trace_id": "mesh-luma-gated-write-coverage-20260511T014707Z-dfc54677:directory-publish",
        "writer_kind": "luma",
        "reader_path": "luma_reader_path",
        "schema_epoch": "post_luma_m0b",
        "luma_profile": "e2e"
      },
      {
        "write_class": "news_report_status",
        "label": "news report/status",
        "status": "pass",
        "trace_id": "mesh-luma-gated-write-coverage-20260511T014707Z-dfc54677:news-report-status",
        "writer_kind": "luma",
        "reader_path": "luma_reader_path",
        "schema_epoch": "post_luma_m0b",
        "luma_profile": "e2e"
      }
    ]
  },
  "luma_gated_write_drills": [
    {
      "write_class": "forum_thread",
      "trace_id": "mesh-luma-gated-write-coverage-20260511T014707Z-dfc54677:forum-thread",
      "status": "pass",
      "writer_kind": "luma",
      "reader_path": "luma_reader_path",
      "schema_epoch": "post_luma_m0b",
      "luma_profile": "e2e"
    },
    {
      "write_class": "forum_comment",
      "trace_id": "mesh-luma-gated-write-coverage-20260511T014707Z-dfc54677:forum-comment",
      "status": "pass",
      "writer_kind": "luma",
      "reader_path": "luma_reader_path",
      "schema_epoch": "post_luma_m0b",
      "luma_profile": "e2e"
    },
    {
      "write_class": "vote_or_aggregate",
      "trace_id": "mesh-luma-gated-write-coverage-20260511T014707Z-dfc54677:vote-or-aggregate",
      "status": "pass",
      "writer_kind": "luma",
      "reader_path": "luma_reader_path",
      "schema_epoch": "post_luma_m0b",
      "luma_profile": "e2e"
    },
    {
      "write_class": "directory_publish",
      "trace_id": "mesh-luma-gated-write-coverage-20260511T014707Z-dfc54677:directory-publish",
      "status": "pass",
      "writer_kind": "luma",
      "reader_path": "luma_reader_path",
      "schema_epoch": "post_luma_m0b",
      "luma_profile": "e2e"
    },
    {
      "write_class": "news_report_status",
      "trace_id": "mesh-luma-gated-write-coverage-20260511T014707Z-dfc54677:news-report-status",
      "status": "pass",
      "writer_kind": "luma",
      "reader_path": "luma_reader_path",
      "schema_epoch": "post_luma_m0b",
      "luma_profile": "e2e"
    }
  ],
  "release_claims": {
    "allowed": [
      "All required LUMA-gated write classes have current LUMA reader-path coverage evidence."
    ],
    "forbidden": [
      "LUMA gate behavior is verified by mesh."
    ],
    "invalidated_by_luma_epoch_change": false
  },
  "failures": []
}
